elision/__init__.py
elision/help.py
elision/random.py
ElisionPy-0.0.8.dist-info/METADATA
ElisionPy-0.0.8.dist-info/WHEEL
ElisionPy-0.0.8.dist-info/top_level.txt
ElisionPy-0.0.8.dist-info/RECORD
